swmm/pandas/__init__.py
swmm/pandas/constants.py
swmm/pandas/py.typed
swmm/pandas/example_data/Model.out
swmm/pandas/example_data/Model.rpt
swmm/pandas/input/README.md
swmm/pandas/input/__init__.py
swmm/pandas/input/_patch.py
swmm/pandas/input/_section_classes.py
swmm/pandas/input/input.py
swmm/pandas/input/model.py
swmm/pandas/output/__init__.py
swmm/pandas/output/output.py
swmm/pandas/output/structure.py
swmm/pandas/output/tools.py
swmm/pandas/report/__init__.py
swmm/pandas/report/report.py
swmm_pandas-0.10.0.dist-info/METADATA
swmm_pandas-0.10.0.dist-info/WHEEL
swmm_pandas-0.10.0.dist-info/licenses/LICENSE.md
swmm_pandas-0.10.0.dist-info/RECORD
