Metadata-Version: 2.3
Name: swmm-pandas
Version: 0.10.0
Summary: SWMM binary outputfile reader and API
Project-URL: Homepage, https://github.com/karosc/swmm-pandas
Author: See README.md
Author-email: Constantine Karos <ckaros@outlook.com>
Maintainer-email: ckaros@outlook.com
License: CC BY 4.0
Keywords: ,hydraulics,hydrology,stormwater,swmm,swmm5
Classifier: Development Status :: 4 - Beta
Classifier: License :: Other/Proprietary License
Classifier: Operating System :: MacOS
Classifier: Operating System :: Microsoft :: Windows
Classifier: Operating System :: POSIX :: Linux
Classifier: Programming Language :: Python :: 3.9
Classifier: Programming Language :: Python :: 3.10
Classifier: Programming Language :: Python :: 3.11
Classifier: Programming Language :: Python :: 3.12
Classifier: Programming Language :: Python :: 3.13
Classifier: Topic :: Scientific/Engineering
Requires-Python: >=3.9
Requires-Dist: julian
Requires-Dist: pandas>=2.1
Requires-Dist: swmm-toolkit>=0.8.1
Provides-Extra: dev
Requires-Dist: coverage; extra == 'dev'
Requires-Dist: furo; extra == 'dev'
Requires-Dist: ipython; extra == 'dev'
Requires-Dist: matplotlib; extra == 'dev'
Requires-Dist: mypy; extra == 'dev'
Requires-Dist: myst-parser; extra == 'dev'
Requires-Dist: nbsphinx; extra == 'dev'
Requires-Dist: numpydoc; extra == 'dev'
Requires-Dist: pytest; extra == 'dev'
Requires-Dist: ruff; extra == 'dev'
Requires-Dist: sphinx; extra == 'dev'
Requires-Dist: sphinx-autobuild; extra == 'dev'
